lindworm/data/rules/__order__.cson
lindworm/data/rules/datatypes.cson
lindworm/data/rules/infix.cson
lindworm/data/rules/infix_assign.cson
lindworm/data/rules/infix_curry.cson
lindworm/data/rules/misc.cson
lindworm/data/rules/shorthands.cson
lindworm/data/templates/default.py.mako
lindworm/header/__init__.py
lindworm/header/classes.py
lindworm/header/functions.py
lindworm/header/lindworm_ops.py
lindworm/header/result.py
lindworm/new_builtins/__init__.py
lindworm/new_builtins/result.py
lindworm/sigurdlib/__init__.py
lindworm/sigurdlib/constants.py
lindworm/sigurdlib/dialect.py
lindworm/sigurdlib/lindworm.py
lindworm/sigurdlib/rule.py
lindworm/sigurdlib/token.py
lindworm/utils/__init__.py
lindworm/utils/_tests.py
lindworm/utils/misc.py
lindworm/utils/pretty.py
lindworm/utils/regex_replace.py
lindworm/utils/tempfile.py
lindworm_language-0.1.0.data/scripts/lindworm
lindworm_language-0.1.0.data/scripts/sigurd
lindworm_language-0.1.0.dist-info/METADATA
lindworm_language-0.1.0.dist-info/WHEEL
lindworm_language-0.1.0.dist-info/top_level.txt
lindworm_language-0.1.0.dist-info/RECORD
